seokbong_cmd/__init__.py
seokbong_cmd/seokbong_cmd.py
seokbong_cmd-2.0.1.dist-info/METADATA
seokbong_cmd-2.0.1.dist-info/WHEEL
seokbong_cmd-2.0.1.dist-info/entry_points.txt
seokbong_cmd-2.0.1.dist-info/top_level.txt
seokbong_cmd-2.0.1.dist-info/RECORD
