Metadata-Version: 2.1
Name: seokbong_cmd
Version: 2.0.1
Summary: Default template for PDM package
Author-email: tbongkim03 <tbongkim03@gmial.com>
License: MIT
Project-URL: HOMEPAGE, https://github.com/tbongkim03/seokbong_cmd
Project-URL: ISSUES, https://github.com/tbongkim03/seokbong_cmd/issues
Requires-Python: >=3.9
Requires-Dist: seokbong-add >=1.0.0
Requires-Dist: seokbong-mul >=1.0.2
Requires-Dist: seokbong-division >=0.3.0
